setup.py
TracBurndownPlugin.egg-info/PKG-INFO
TracBurndownPlugin.egg-info/SOURCES.txt
TracBurndownPlugin.egg-info/dependency_links.txt
TracBurndownPlugin.egg-info/entry_points.txt
TracBurndownPlugin.egg-info/not-zip-safe
TracBurndownPlugin.egg-info/requires.txt
TracBurndownPlugin.egg-info/top_level.txt
customBurndownChart/__init__.py
customBurndownChart/config.py
customBurndownChart/embed.py
customBurndownChart/inject.py
customBurndownChart/prefs.py
customBurndownChart/tooltip.py