Metadata-Version: 1.0
Name: TracBurndownPlugin
Version: 0.1
Summary: Burndown chart plugin for milestones in Trac
Home-page: http://www.lshift.net/
Author: Lee Wei
Author-email: leewei@lshift.net
License: BSD
Download-URL: http://www.lshift.net/
Keywords: trac burndown chart plugin
Platform: UNKNOWN
Classifier: Intended Audience :: Developers
Classifier: License :: OSI Approved :: BSD License
Classifier: Operating System :: Unix
Classifier: Programming Language :: Python
Classifier: Topic :: Software Development :: Bug Tracking
Classifier: Topic :: Software Development :: Version Control
